pubcontrol_wordpress/config.py
pubcontrol_wordpress/install.py
pubcontrol_wordpress/main.py
pubcontrol_wordpress/reference.py
pubcontrol_wordpress/views.py
pubcontrol_wordpress/wordpress.py
pubcontrol_wordpress/templates/button.j2
pubcontrol_wordpress/templates/comment.j2
pubcontrol_wordpress/templates/post.j2
pubcontrol_wordpress/templates/ini/__init__.py
pubcontrol_wordpress/templates/ini/config.j2
pubcontrol_wordpress-0.0.0.6.dist-info/DESCRIPTION.rst
pubcontrol_wordpress-0.0.0.6.dist-info/METADATA
pubcontrol_wordpress-0.0.0.6.dist-info/RECORD
pubcontrol_wordpress-0.0.0.6.dist-info/WHEEL
pubcontrol_wordpress-0.0.0.6.dist-info/metadata.json
pubcontrol_wordpress-0.0.0.6.dist-info/top_level.txt
